matrixzulipbridge/__init__.py
matrixzulipbridge/__main__.py
matrixzulipbridge/appservice.py
matrixzulipbridge/command_parse.py
matrixzulipbridge/control_room.py
matrixzulipbridge/direct_room.py
matrixzulipbridge/event_queue.py
matrixzulipbridge/organization_room.py
matrixzulipbridge/personal_room.py
matrixzulipbridge/room.py
matrixzulipbridge/space_room.py
matrixzulipbridge/stream_room.py
matrixzulipbridge/types.py
matrixzulipbridge/under_organization_room.py
matrixzulipbridge/version.py
matrixzulipbridge/version.txt
matrixzulipbridge/websocket.py
matrixzulipbridge/zulip.py
matrixzulipbridge-0.4.1.dist-info/LICENSE
matrixzulipbridge-0.4.1.dist-info/METADATA
matrixzulipbridge-0.4.1.dist-info/WHEEL
matrixzulipbridge-0.4.1.dist-info/entry_points.txt
matrixzulipbridge-0.4.1.dist-info/RECORD
