Metadata-Version: 2.1
Name: matrixzulipbridge
Version: 0.4.1
Summary: A Matrix puppeting bridge for Zulip
License: AGPL-3.0-or-later
Author: GearKite
Author-email: emgh@em.id.lv
Requires-Python: >=3.10,<4.0
Classifier: License :: OSI Approved :: GNU Affero General Public License v3 or later (AGPLv3+)
Classifier: Programming Language :: Python :: 3
Classifier: Programming Language :: Python :: 3.10
Classifier: Programming Language :: Python :: 3.11
Classifier: Programming Language :: Python :: 3.12
Requires-Dist: beautifulsoup4 (>=4.6.2,<5.0.0)
Requires-Dist: bidict (>=0.22,<0.23)
Requires-Dist: coloredlogs (>=15,<16)
Requires-Dist: emoji (>=2,<3)
Requires-Dist: markdownify (>=0.10,<0.11)
Requires-Dist: mautrix (>=0.20,<0.21)
Requires-Dist: python-dotenv (>=1,<2)
Requires-Dist: ruamel-yaml (>=0.16,<0.18)
Requires-Dist: zulip (>=0.9,<0.10)
Requires-Dist: zulip-emoji-mapping (>=1.0.1,<2.0.0)
